MANIFEST.in
README
setup.py
sex.py
docs/index.rst
docs/syntax.rst
docs/usage.rst
examples/README
examples/exam.sex
examples/fibonacci.sex
examples/foo.sex
examples/hacker.sex
examples/hello.sex
examples/praise.sex
examples/screenshot.sex
examples/traceback.sex
sexpy/__init__.py
sexpy/parser.py
sexpy/toplevel.py
sexpy/translator.py
sexpy.egg-info/PKG-INFO
sexpy.egg-info/SOURCES.txt
sexpy.egg-info/dependency_links.txt
sexpy.egg-info/top_level.txt