Metadata-Version: 1.0
Name: sexpy
Version: 0.2
Summary: S-expression syntax for Python
Home-page: http://python.org/pypi/sexpy
Author: Ero-sennin
Author-email: densetsu.no.ero.sennin@gmail.com
License: GPL-2
Platform: platform-independent
Classifier: Development Status :: 3 - Alpha
Classifier: Environment :: Console
Classifier: License :: OSI Approved :: GNU General Public License (GPL)
Classifier: Operating System :: OS Independent
Classifier: Programming Language :: Python
